{
	"_id":"Traffic",
    "_class" : "mx.infotec.smartcity.backend.model.Notification",
	"name":"Traffic",
	"subnotifications":["TrafficJam",
						"ModerateTrafficJam",
						"StandstillTrafficJam",						
						"HeavyTrafficJam",
						"MinorAccident",
						"CarAccident",						
						"CarInWrongDirection",						
						"CarStopped",
						"Roadworks",
						"RoadClosed",
						"Hazard On Road",
						"Pothole",
						"CongestionOnRoad",
						"BikersInjured",
						"AlligatorCracking"]
}
{
	"_id":"Weather",
    "_class" : "mx.infotec.smartcity.backend.model.Notification",
	"name":"Weather",
	"subnotifications":["Rainfall",
						"Temperature",
						"HighTemperature",
						"LowTemperature",
						"HeatWave",
						"ColdWave",
						"Ice",
						"RelativeHumidity",
						"Wind",
						"Flood",
						"Fog",
						"Tornado",
						"Tsunami",
						"Snow",
						"Storm",
						"TropicalCyclone",
						"TropicalStorm",
						"Hurricane"
						]
}
{
	"_id":"Environment",
    "_class" : "mx.infotec.smartcity.backend.model.Notification",
	"name":"Environment",
	"subnotifications":["Smog",
						"AirPollution",
						"WaterPollution",
						"PreContingencyAlert",
						"ContingencyAlert",
						"CO",
						"NO2",
						"SO2",
						"O3",
						"PM10",
						"VolcanoGas",
						"IndustrialGas",
						"VehicularGas",
						"AgricultureGas",
						"Odors",
						"Radioactive"]
}
{
	"_id":"Pollen",
    "_class" : "mx.infotec.smartcity.backend.model.Notification",
	"name":"Pollen",
	"subnotifications":["Symptoms",
						"PollenLevel",
						"PollenConcentration",
						"Sinuspressure",
						"Runnynose",
						"Wateryeyes",
						"Cough",
						"Nasalcongestion"]
}
{
	"_id":"Health",
    "_class" : "mx.infotec.smartcity.backend.model.Notification",
	"name":"Health",
	"subnotifications":["AsthmaAttacks",
						"BumpedPatient",
						"FallenPatient",
						"HeartAttack"
						]
}
{
	"_id":"Security",
    "_class" : "mx.infotec.smartcity.backend.model.Notification",
	"name":"Security",
	"subnotifications":["Assaults",
						"Robbery",
						"SuspiciousAction",
						"CivilDisorder",
						"BuildingFire",
						"ForestFire"
						]
}
{
	"_id":"SOSAlerts",
    "_class" : "mx.infotec.smartcity.backend.model.Notification",
	"name":"SOS Alerts",
	"subnotifications":["Shelter",
						"CollectionCenter",
						"Hospital",
						"BloodBank",
						"Earthquake",
						"Collapse",
						"CollapsedBuilding",
						"BuildingOnTheVergeOfCollapse",
						"Sinking",
						"MajorCrack",
						"MinorCrack",
						"LightTransformerDropped",
						"FallenLightPost",
						"Fire",
						"WaterShortage",
						"WithoutLightService",
						"GasLeak"]
}
